{
  "wk_000005476": {
    "workId": "wk_000005476",
    "title": "커피 문",
    "category": "manga",
    "domain": "subculture",
    "externalIds": {
      "wikidata": "Q130308184"
    },
    "titles": {
      "ko": "커피 문",
      "en": "Coffee Moon",
      "ja": "コーヒームーン"
    },
    "extensions": {
      "ingestChannel": "wikidata_ko_manga",
      "ingestSource": "wikidata_ko"
    }
  },
  "wk_000005955": {
    "workId": "wk_000005955",
    "title": "마호라바",
    "category": "manga",
    "domain": "subculture",
    "externalIds": {
      "wikidata": "Q1322197"
    },
    "titles": {
      "ko": "마호라바",
      "en": "Mahoraba",
      "ja": "まほらば"
    },
    "releaseYear": 2000,
    "creator": "Akira Kojima",
    "extensions": {
      "ingestChannel": "wikidata_ko_manga",
      "ingestSource": "wikidata_ko"
    }
  },
  "wk_000006860": {
    "workId": "wk_000006860",
    "title": "리틀 포레스트",
    "category": "manga",
    "domain": "subculture",
    "externalIds": {
      "wikidata": "Q16351209"
    },
    "titles": {
      "ko": "리틀 포레스트",
      "en": "Little Forest",
      "ja": "リトル・フォレスト"
    },
    "extensions": {
      "ingestChannel": "wikidata_ko_manga",
      "ingestSource": "wikidata_ko"
    }
  },
  "wk_000006917": {
    "workId": "wk_000006917",
    "title": "겁쟁이 페달",
    "category": "manga",
    "domain": "subculture",
    "externalIds": {
      "wikidata": "Q1661633"
    },
    "titles": {
      "ko": "겁쟁이 페달",
      "en": "Yowamushi Pedal",
      "ja": "弱虫ペダル"
    },
    "releaseYear": 2013,
    "creator": "Wataru Watanabe",
    "extensions": {
      "ingestChannel": "wikidata_ko_manga",
      "ingestSource": "wikidata_ko"
    }
  }
}
