{
  "wk_000004460": {
    "workId": "wk_000004460",
    "title": "망내인",
    "category": "book",
    "domain": "subculture",
    "externalIds": {
      "wikidata": "Q108731705"
    },
    "titles": {
      "ko": "망내인",
      "en": "Second Sister"
    },
    "releaseYear": 2017,
    "creator": "Chan Ho-kei",
    "extensions": {
      "ingestChannel": "wikidata_ko_book",
      "ingestSource": "wikidata_ko"
    }
  },
  "wk_000006951": {
    "workId": "wk_000006951",
    "title": "레이첼 다이어",
    "category": "book",
    "domain": "subculture",
    "externalIds": {
      "wikidata": "Q111955489"
    },
    "titles": {
      "ko": "레이첼 다이어",
      "en": "Rachel Dyer"
    },
    "releaseYear": 1828,
    "creator": "John Neal",
    "extensions": {
      "ingestChannel": "wikidata_ko_book",
      "ingestSource": "wikidata_ko"
    }
  }
}
