{
  "wk_000000319": {
    "workId": "wk_000000319",
    "title": "에덴스 제로",
    "titles": {
      "ko": "에덴스 제로",
      "en": "Edens Zero",
      "ja": "EDENS ZERO"
    },
    "category": "manga",
    "domain": "subculture",
    "creator": "마시마 히로",
    "releaseYear": 2018,
    "tags": [
      "SF",
      "모험",
      "우주",
      "우정"
    ],
    "extensions": {
      "coverageSprint04ExternalId": "tmdb",
      "ingestChannel": "manual_wikidata",
      "ingestSource": "manual"
    },
    "legacyIds": [
      "sub_manga_edens-zero_2018"
    ],
    "externalIds": {
      "tmdb": "97525",
      "wikidata": "Q54667228"
    },
    "qualitySignals": {
      "externalIdVerified": true
    }
  },
  "wk_000001894": {
    "workId": "wk_000001894",
    "title": "이 세계는 너무나 불완전하다",
    "category": "manga",
    "domain": "subculture",
    "externalIds": {
      "wikidata": "Q113213531"
    },
    "titles": {
      "ko": "이 세계는 너무나 불완전하다",
      "en": "Quality Assurance in Another World",
      "ja": "この世界は不完全すぎる"
    },
    "releaseYear": 2020,
    "extensions": {
      "ingestChannel": "wikidata_ko_manga",
      "ingestSource": "wikidata_ko"
    }
  },
  "wk_000002517": {
    "workId": "wk_000002517",
    "title": "명탐정 카게맨",
    "category": "manga",
    "domain": "subculture",
    "externalIds": {
      "wikidata": "Q11414698"
    },
    "titles": {
      "ko": "명탐정 카게맨",
      "en": "Q11414698",
      "ja": "名たんていカゲマン"
    },
    "extensions": {
      "ingestChannel": "wikidata_ko_manga",
      "ingestSource": "wikidata_ko"
    }
  },
  "wk_000006519": {
    "workId": "wk_000006519",
    "title": "네? 사내 시스템을 전부 혼자 관리하는 저를 해고한다구요?",
    "category": "manga",
    "domain": "subculture",
    "externalIds": {
      "wikidata": "Q139720373"
    },
    "titles": {
      "ko": "네? 사내 시스템을 전부 혼자 관리하는 저를 해고한다구요?",
      "en": "Fired? But I Maintain All the Software!",
      "ja": "え、社内システム全てワンオペしている私を解雇ですか?"
    },
    "extensions": {
      "ingestChannel": "wikidata_ko_manga",
      "ingestSource": "wikidata_ko"
    }
  },
  "wk_000008898": {
    "workId": "wk_000008898",
    "title": "에트랑제 시리즈",
    "category": "manga",
    "domain": "subculture",
    "externalIds": {
      "wikidata": "Q24864422"
    },
    "titles": {
      "ko": "에트랑제 시리즈",
      "en": "Umibe no Étranger",
      "ja": "海辺のエトランゼ"
    },
    "creator": "Kanna Kii",
    "extensions": {
      "ingestChannel": "wikidata_ko_manga",
      "ingestSource": "wikidata_ko"
    }
  }
}
