{
  "wk_000004540": {
    "workId": "wk_000004540",
    "title": "열쇠",
    "category": "movie",
    "domain": "subculture",
    "externalIds": {
      "wikidata": "Q1056946"
    },
    "titles": {
      "ko": "열쇠",
      "en": "Odd Obsession",
      "ja": "鍵"
    },
    "releaseYear": 1959,
    "extensions": {
      "ingestChannel": "wikidata_ko_movie",
      "ingestSource": "wikidata_ko"
    }
  },
  "wk_000007555": {
    "workId": "wk_000007555",
    "title": "전염병의 첫번째 파도",
    "category": "movie",
    "domain": "subculture",
    "externalIds": {
      "wikidata": "Q107404441"
    },
    "titles": {
      "ko": "전염병의 첫번째 파도",
      "en": "The First Wave",
      "ja": "ニューヨーク 第1波"
    },
    "releaseYear": 2021,
    "extensions": {
      "ingestChannel": "wikidata_ko_movie",
      "ingestSource": "wikidata_ko"
    }
  },
  "wk_000007885": {
    "workId": "wk_000007885",
    "title": "송곳니",
    "category": "movie",
    "domain": "subculture",
    "externalIds": {
      "wikidata": "Q1075918"
    },
    "titles": {
      "ko": "송곳니",
      "en": "Dogtooth",
      "ja": "籠の中の乙女"
    },
    "releaseYear": 2009,
    "extensions": {
      "ingestChannel": "wikidata_ko_movie",
      "ingestSource": "wikidata_ko"
    }
  },
  "wk_000008792": {
    "workId": "wk_000008792",
    "title": "텍사스 전기톱 학살",
    "category": "movie",
    "domain": "subculture",
    "externalIds": {
      "wikidata": "Q108145849"
    },
    "titles": {
      "ko": "텍사스 전기톱 학살",
      "en": "Texas Chainsaw Massacre",
      "ja": "悪魔のいけにえ -レザーフェイス・リターンズ-"
    },
    "releaseYear": 2022,
    "extensions": {
      "ingestChannel": "wikidata_ko_movie",
      "ingestSource": "wikidata_ko"
    }
  }
}
