{
  "wk_000000572": {
    "workId": "wk_000000572",
    "title": "조이드 제네시스",
    "category": "animation",
    "domain": "subculture",
    "externalIds": {
      "wikidata": "Q1022078"
    },
    "titles": {
      "ko": "조이드 제네시스",
      "en": "Zoids: Genesis",
      "ja": "ゾイドジェネシス"
    },
    "extensions": {
      "ingestChannel": "wikidata_ko_animation",
      "ingestSource": "wikidata_ko"
    }
  },
  "wk_000001597": {
    "workId": "wk_000001597",
    "title": "유희왕 고 러시!!",
    "category": "animation",
    "domain": "subculture",
    "externalIds": {
      "wikidata": "Q111548990"
    },
    "titles": {
      "ko": "유희왕 고 러시!!",
      "en": "Yu-Gi-Oh! Go Rush!!",
      "ja": "遊☆戯☆王ゴーラッシュ!!"
    },
    "extensions": {
      "ingestChannel": "wikidata_ko_animation",
      "ingestSource": "wikidata_ko"
    }
  },
  "wk_000003276": {
    "workId": "wk_000003276",
    "title": "드래곤볼 DAIMA",
    "category": "animation",
    "domain": "subculture",
    "externalIds": {
      "wikidata": "Q123022503"
    },
    "titles": {
      "ko": "드래곤볼 DAIMA",
      "en": "Dragon Ball Daima",
      "ja": "ドラゴンボールDAIMA"
    },
    "extensions": {
      "ingestChannel": "wikidata_ko_animation",
      "ingestSource": "wikidata_ko"
    }
  },
  "wk_000004066": {
    "workId": "wk_000004066",
    "title": "호텔 인휴먼즈",
    "category": "animation",
    "domain": "subculture",
    "externalIds": {
      "wikidata": "Q131048074"
    },
    "titles": {
      "ko": "호텔 인휴먼즈",
      "en": "Hotel Inhumans",
      "ja": "ホテル・インヒューマンズ"
    },
    "extensions": {
      "ingestChannel": "wikidata_ko_animation",
      "ingestSource": "wikidata_ko"
    }
  },
  "wk_000007094": {
    "workId": "wk_000007094",
    "title": "하퍼스 아일랜드",
    "category": "animation",
    "domain": "subculture",
    "externalIds": {
      "wikidata": "Q440938"
    },
    "titles": {
      "ko": "하퍼스 아일랜드",
      "en": "Harper's Island",
      "ja": "ハーパーズ・アイランド 惨劇の島"
    },
    "extensions": {
      "ingestChannel": "wikidata_ko_animation",
      "ingestSource": "wikidata_ko"
    }
  },
  "wk_000009995": {
    "workId": "wk_000009995",
    "title": "수퍼 멍멍이 레츠고 태피",
    "category": "animation",
    "domain": "subculture",
    "externalIds": {
      "wikidata": "Q987783"
    },
    "titles": {
      "ko": "수퍼 멍멍이 레츠고 태피",
      "en": "Wan Wan Celeb Soreyuke! Tetsunoshin",
      "ja": "ワンワンセレプー それゆけ!徹之進"
    },
    "extensions": {
      "ingestChannel": "wikidata_ko_animation",
      "ingestSource": "wikidata_ko"
    }
  }
}
