{
  "wk_000000771": {
    "workId": "wk_000000771",
    "title": "러브 셔플",
    "category": "drama",
    "domain": "subculture",
    "externalIds": {
      "wikidata": "Q1036991"
    },
    "titles": {
      "ko": "러브 셔플",
      "en": "Love Shuffle",
      "ja": "ラブシャッフル"
    },
    "extensions": {
      "ingestChannel": "wikidata_ko_drama",
      "ingestSource": "wikidata_ko"
    }
  },
  "wk_000001044": {
    "workId": "wk_000001044",
    "title": "Wish You: 나의 마음속 너의 멜로디",
    "category": "drama",
    "domain": "subculture",
    "externalIds": {
      "wikidata": "Q104884904"
    },
    "titles": {
      "ko": "Wish You: 나의 마음속 너의 멜로디",
      "en": "Wish You"
    },
    "extensions": {
      "ingestChannel": "wikidata_ko_drama",
      "ingestSource": "wikidata_ko"
    }
  },
  "wk_000003321": {
    "workId": "wk_000003321",
    "title": "더 듀엣",
    "category": "drama",
    "domain": "subculture",
    "externalIds": {
      "wikidata": "Q109460769"
    },
    "titles": {
      "ko": "더 듀엣",
      "en": "The Duet"
    },
    "extensions": {
      "ingestChannel": "wikidata_ko_drama",
      "ingestSource": "wikidata_ko"
    }
  },
  "wk_000004267": {
    "workId": "wk_000004267",
    "title": "칼의 전쟁",
    "category": "drama",
    "domain": "subculture",
    "externalIds": {
      "wikidata": "Q110117874"
    },
    "titles": {
      "ko": "칼의 전쟁",
      "en": "Q110117874"
    },
    "extensions": {
      "ingestChannel": "wikidata_ko_drama",
      "ingestSource": "wikidata_ko"
    }
  },
  "wk_000004562": {
    "workId": "wk_000004562",
    "title": "아바타로전대 돈브라더즈",
    "category": "drama",
    "domain": "subculture",
    "externalIds": {
      "wikidata": "Q110659846"
    },
    "titles": {
      "ko": "아바타로전대 돈브라더즈",
      "en": "Avataro Sentai Donbrothers",
      "ja": "暴太郎戦隊ドンブラザーズ"
    },
    "extensions": {
      "ingestChannel": "wikidata_ko_drama",
      "ingestSource": "wikidata_ko"
    }
  },
  "wk_000006234": {
    "workId": "wk_000006234",
    "title": "스텝파더 스텝",
    "category": "drama",
    "domain": "subculture",
    "externalIds": {
      "wikidata": "Q11312272"
    },
    "titles": {
      "ko": "스텝파더 스텝",
      "en": "Q11312272",
      "ja": "ステップファザー・ステップ"
    },
    "releaseYear": 1993,
    "creator": "Miyuki Miyabe",
    "extensions": {
      "ingestChannel": "wikidata_ko_drama",
      "ingestSource": "wikidata_ko"
    }
  },
  "wk_000006509": {
    "workId": "wk_000006509",
    "title": "호러 아쿠시덴타루",
    "category": "drama",
    "domain": "subculture",
    "externalIds": {
      "wikidata": "Q11338012"
    },
    "titles": {
      "ko": "호러 아쿠시덴타루",
      "en": "Horror Accidental",
      "ja": "ホラー アクシデンタル"
    },
    "extensions": {
      "ingestChannel": "wikidata_ko_drama",
      "ingestSource": "wikidata_ko"
    }
  },
  "wk_000007092": {
    "workId": "wk_000007092",
    "title": "닭강정",
    "category": "drama",
    "domain": "subculture",
    "externalIds": {
      "wikidata": "Q114347363"
    },
    "titles": {
      "ko": "닭강정",
      "en": "Chicken Nugget",
      "ja": "タッカンジョン"
    },
    "extensions": {
      "ingestChannel": "wikidata_ko_drama",
      "ingestSource": "wikidata_ko"
    }
  },
  "wk_000007562": {
    "workId": "wk_000007562",
    "title": "상암동 클라스",
    "category": "drama",
    "domain": "subculture",
    "externalIds": {
      "wikidata": "Q115166233"
    },
    "titles": {
      "ko": "상암동 클라스",
      "en": "Sangam-Dong Class"
    },
    "extensions": {
      "ingestChannel": "wikidata_ko_drama",
      "ingestSource": "wikidata_ko"
    }
  },
  "wk_000007578": {
    "workId": "wk_000007578",
    "title": "캡틴",
    "category": "drama",
    "domain": "subculture",
    "externalIds": {
      "wikidata": "Q115300951"
    },
    "titles": {
      "ko": "캡틴",
      "en": "CAP-TEEN"
    },
    "extensions": {
      "ingestChannel": "wikidata_ko_drama",
      "ingestSource": "wikidata_ko"
    }
  }
}
