{
  "wk_000000582": {
    "workId": "wk_000000582",
    "title": "돕식: 약물의 늪",
    "category": "drama",
    "domain": "subculture",
    "externalIds": {
      "wikidata": "Q101420707"
    },
    "titles": {
      "ko": "돕식: 약물의 늪",
      "en": "Dopesick",
      "ja": "DOPESICK アメリカを蝕むオピオイド危機"
    },
    "extensions": {
      "ingestChannel": "wikidata_ko_drama",
      "ingestSource": "wikidata_ko"
    }
  },
  "wk_000001790": {
    "workId": "wk_000001790",
    "title": "KBS 월드뉴스 (KBS 2TV)",
    "category": "drama",
    "domain": "subculture",
    "externalIds": {
      "wikidata": "Q108362883"
    },
    "titles": {
      "ko": "KBS 월드뉴스 (KBS 2TV)",
      "en": "KBS World News"
    },
    "extensions": {
      "ingestChannel": "wikidata_ko_drama",
      "ingestSource": "wikidata_ko"
    }
  },
  "wk_000004473": {
    "workId": "wk_000004473",
    "title": "닥터 로이어",
    "category": "drama",
    "domain": "subculture",
    "externalIds": {
      "wikidata": "Q110420048"
    },
    "titles": {
      "ko": "닥터 로이어",
      "en": "Doctor Lawyer"
    },
    "extensions": {
      "ingestChannel": "wikidata_ko_drama",
      "ingestSource": "wikidata_ko"
    }
  },
  "wk_000004937": {
    "workId": "wk_000004937",
    "title": "진검승부",
    "category": "drama",
    "domain": "subculture",
    "externalIds": {
      "wikidata": "Q111592240"
    },
    "titles": {
      "ko": "진검승부",
      "en": "Bad Prosecutor",
      "ja": "真剣勝負 (テレビドラマ)"
    },
    "extensions": {
      "ingestChannel": "wikidata_ko_drama",
      "ingestSource": "wikidata_ko"
    }
  },
  "wk_000005195": {
    "workId": "wk_000005195",
    "title": "남자가 울지 않는 밤은 없다",
    "category": "drama",
    "domain": "subculture",
    "externalIds": {
      "wikidata": "Q11230208"
    },
    "titles": {
      "ko": "남자가 울지 않는 밤은 없다",
      "en": "Q11230208",
      "ja": "男が泣かない夜はない"
    },
    "extensions": {
      "ingestChannel": "wikidata_ko_drama",
      "ingestSource": "wikidata_ko"
    }
  },
  "wk_000005252": {
    "workId": "wk_000005252",
    "title": "대왕의 길",
    "category": "drama",
    "domain": "subculture",
    "externalIds": {
      "wikidata": "Q11232449"
    },
    "titles": {
      "ko": "대왕의 길",
      "en": "Way of the Great King",
      "ja": "大王の道"
    },
    "extensions": {
      "ingestChannel": "wikidata_ko_drama",
      "ingestSource": "wikidata_ko"
    }
  },
  "wk_000006320": {
    "workId": "wk_000006320",
    "title": "트러블맨",
    "category": "drama",
    "domain": "subculture",
    "externalIds": {
      "wikidata": "Q11321818"
    },
    "titles": {
      "ko": "트러블맨",
      "en": "Q11321818",
      "ja": "トラブルマン"
    },
    "extensions": {
      "ingestChannel": "wikidata_ko_drama",
      "ingestSource": "wikidata_ko"
    }
  },
  "wk_000006718": {
    "workId": "wk_000006718",
    "title": "톡파원 25시",
    "category": "drama",
    "domain": "subculture",
    "externalIds": {
      "wikidata": "Q113543676"
    },
    "titles": {
      "ko": "톡파원 25시",
      "en": "Talk Correspondent 25 O'Clock"
    },
    "extensions": {
      "ingestChannel": "wikidata_ko_drama",
      "ingestSource": "wikidata_ko"
    }
  },
  "wk_000008283": {
    "workId": "wk_000008283",
    "title": "소녀 리버스",
    "category": "drama",
    "domain": "subculture",
    "externalIds": {
      "wikidata": "Q116278166"
    },
    "titles": {
      "ko": "소녀 리버스",
      "en": "Girl Reverse",
      "ja": "GIRL REVERSE"
    },
    "extensions": {
      "ingestChannel": "wikidata_ko_drama",
      "ingestSource": "wikidata_ko"
    }
  },
  "wk_000009267": {
    "workId": "wk_000009267",
    "title": "아틀란티스에서 온 사나이",
    "category": "drama",
    "domain": "subculture",
    "externalIds": {
      "wikidata": "Q1195481"
    },
    "titles": {
      "ko": "아틀란티스에서 온 사나이",
      "en": "Man from Atlantis",
      "ja": "アトランティスから来た男"
    },
    "extensions": {
      "ingestChannel": "wikidata_ko_drama",
      "ingestSource": "wikidata_ko"
    }
  },
  "wk_000009734": {
    "workId": "wk_000009734",
    "title": "엘 말레피시오",
    "category": "drama",
    "domain": "subculture",
    "externalIds": {
      "wikidata": "Q123152606"
    },
    "titles": {
      "ko": "엘 말레피시오",
      "en": "El maleficio"
    },
    "extensions": {
      "ingestChannel": "wikidata_ko_drama",
      "ingestSource": "wikidata_ko"
    }
  },
  "wk_000009864": {
    "workId": "wk_000009864",
    "title": "꿈나무 TV 여행",
    "category": "drama",
    "domain": "subculture",
    "externalIds": {
      "wikidata": "Q124071665"
    },
    "titles": {
      "ko": "꿈나무 TV 여행",
      "en": "Q124071665"
    },
    "extensions": {
      "ingestChannel": "wikidata_ko_drama",
      "ingestSource": "wikidata_ko"
    }
  }
}
